realms/__init__.py
realms/mundus.py
realms/realm.py
realms/registry.py
realms/cli/__init__.py
realms/cli/constants.py
realms/cli/dfx.template.json
realms/cli/generator.py
realms/cli/logging_config.py
realms/cli/main.py
realms/cli/models.py
realms/cli/requirements.txt
realms/cli/utils.py
realms/cli/commands/__init__.py
realms/cli/commands/create.py
realms/cli/commands/db.py
realms/cli/commands/deploy.py
realms/cli/commands/export_data.py
realms/cli/commands/extension.py
realms/cli/commands/import_data.py
realms/cli/commands/init.py
realms/cli/commands/mundus.py
realms/cli/commands/ps.py
realms/cli/commands/registry.py
realms/cli/commands/run.py
realms/cli/commands/self_register.py
realms/cli/commands/shell.py
realms/ggg/README.md
realms/ggg/__init__.py
realms/ggg/balance.py
realms/ggg/call.py
realms/ggg/codex.py
realms/ggg/constants.py
realms/ggg/contract.py
realms/ggg/dispute.py
realms/ggg/human.py
realms/ggg/identity.py
realms/ggg/instrument.py
realms/ggg/invoice.py
realms/ggg/land.py
realms/ggg/license.py
realms/ggg/mandate.py
realms/ggg/member.py
realms/ggg/notification.py
realms/ggg/organization.py
realms/ggg/payment_account.py
realms/ggg/permission.py
realms/ggg/proposal.py
realms/ggg/realm.py
realms/ggg/registry.py
realms/ggg/service.py
realms/ggg/status.py
realms/ggg/task.py
realms/ggg/task_execution.py
realms/ggg/task_schedule.py
realms/ggg/task_step.py
realms/ggg/token.py
realms/ggg/trade.py
realms/ggg/transfer.py
realms/ggg/treasury.py
realms/ggg/user.py
realms/ggg/user_profile.py
realms/ggg/vote.py
realms/ggg/zone.py
realms_gos-0.2.7.dist-info/licenses/LICENSE
realms_gos-0.2.7.dist-info/METADATA
realms_gos-0.2.7.dist-info/WHEEL
realms_gos-0.2.7.dist-info/entry_points.txt
realms_gos-0.2.7.dist-info/top_level.txt
realms_gos-0.2.7.dist-info/RECORD
